{
  "name": "whatDoYouWant",
  "title": "Чем мы можем быть Вам полезны?",
  "type": "radios",
  "variables": [
    {
      "varname": "create-system",
      "vartitle": "Создать систему продаж в интернете",
      "next": {
        "name": "companyName",
        "title": "Название Вашей компании",
        "type": "text",
        "variables": [
          {
            "varname": "companyName",
            "vartitle": "Название компании",
            "next": {
              "name": "fieldOfActivity",
              "title": "Сфера деятельности",
              "type": "text",
              "variables": [
                {
                  "varname": "fieldOfActivity",
                  "vartitle": "Сфера деятельности",
                  "next": {
                    "name": "yourCity",
                    "title": "В каком городе работает компания",
                    "type": "text",
                    "variables": [
                      {
                        "varname": "yourCity",
                        "vartitle": " Город",
                        "next": {
                          "name": "haveSite",
                          "title": "Есть ли у Вас сайт?",
                          "type": "radios",
                          "variables": [
                            {
                              "varname": "yes",
                              "vartitle": "Да",
                              "next": {
                                "name": "siteAddress",
                                "title": "Введите адрес вашего сайта",
                                "type": "text",
                                "variables": [
                                  {
                                    "varname": "address",
                                    "vartitle": "адрес",
                                    "next": {
                                      "name": "yourСompetitors",
                                      "title": "Кто Ваши конкуренты",
                                      "type": "textarea",
                                      "variables": [
                                        {
                                          "varname": "yourСompetitors",
                                          "vartitle": "Кто Ваши конкуренты",
                                          "next": {
                                            "name": "contacts",
                                            "title": "Оставьте Ваши контакты",
                                            "type": "text",
                                            "variables": [
                                              {
                                                "varname": "name",
                                                "vartitle": "Имя",
                                                "next": null
                                              },
                                              {
                                                "varname": "phone",
                                                "datavalidator": "\\d{11}",
                                                "vartitle": "Телефон",
                                                "next": null
                                              },
                                              {
                                                "varname": "email",
                                                "datavalidator": ".+@.+\..+",
                                                "vartitle": "Электронная почта",
                                                "next": null
                                              }
                                            ]
                                          }
                                        }
                                      ]
                                    }
                                  }
                                ]
                              }
                            },
                            {
                              "varname": "no",
                              "vartitle": "Нет",
                              "next": {
                                "name": "yourСompetitors",
                                "title": "Кто Ваши конкуренты",
                                "type": "textarea",
                                "variables": [
                                  {
                                    "varname": "yourСompetitors",
                                    "vartitle": "Кто Ваши конкуренты",
                                    "next": {
                                      "name": "contacts",
                                      "title": "Оставьте Ваши контакты",
                                      "type": "text",
                                      "variables": [
                                        {
                                          "varname": "name",
                                          "vartitle": "Имя",
                                          "next": null
                                        },
                                        {
                                          "varname": "phone",
                                          "datavalidator": "\\d{11}",
                                          "vartitle": "Телефон",
                                          "next": null
                                        },
                                        {
                                          "varname": "email",
                                          "datavalidator": ".+@.+\..+",
                                          "vartitle": "Электронная почта",
                                          "next": null
                                        }
                                      ]
                                    }
                                  }
                                ]
                              }
                            }
                          ]
                        }
                      }
                    ]
                  }
                }
              ]
            }
          }
        ]
      }
    },
    {
      "varname": "create-system",
      "vartitle": "Создать сайт",
      "next": {
        "name": "whichSite",
        "title": "Какой сайт вы хотите?",
        "type": "radios",
        "variables": [
          {
            "varname": "image",
            "vartitle": "Имиджевый",
            "next": {
              "name": "companyName",
              "title": "Название Вашей компании",
              "type": "text",
              "variables": [
                {
                  "varname": "companyName",
                  "vartitle": "Название компании",
                  "next": {
                    "name": "fieldOfActivity",
                    "title": "Сфера деятельности",
                    "type": "text",
                    "variables": [
                      {
                        "varname": "fieldOfActivity",
                        "vartitle": "Сфера деятельности",
                        "next": {
                          "name": "yourCity",
                          "title": "В каком городе работает компания",
                          "type": "text",
                          "variables": [
                            {
                              "varname": "yourCity",
                              "vartitle": " Город",
                              "next": {
                                "name": "yourСompetitors",
                                "title": "Кто Ваши конкуренты",
                                "type": "textarea",
                                "variables": [
                                  {
                                    "varname": "yourСompetitors",
                                    "vartitle": "Кто Ваши конкуренты",
                                    "next": {
                                      "name": "contacts",
                                      "title": "Оставьте Ваши контакты",
                                      "type": "text",
                                      "variables": [
                                        {
                                          "varname": "name",
                                          "vartitle": "Имя",
                                          "next": null
                                        },
                                        {
                                          "varname": "phone",
                                          "datavalidator": "\\d{11}",
                                          "vartitle": "Телефон",
                                          "next": null
                                        },
                                        {
                                          "varname": "email",
                                          "datavalidator": ".+@.+\..+",
                                          "vartitle": "Электронная почта",
                                          "next": null
                                        }
                                      ]
                                    }
                                  }
                                ]
                              }
                            }
                          ]
                        }
                      }
                    ]
                  }
                }
              ]
            }
          },
          {
            "varname": "seller",
            "vartitle": "Продающий",
            "next": {
              "name": "howMuchCategories",
              "title": "Сколько товарных категорий",
              "type": "text",
              "variables": [
                {
                  "varname": "howMuchCategories",
                  "vartitle": "Сколько товарных категорий",
                  "next": {
                    "name": "needPayment",
                    "title": "Нужна ли возможность онлайн оплаты",
                    "type": "radios",
                    "variables": [
                      {
                        "varname": "yes",
                        "vartitle": "Да",
                        "next": {
                          "name": "need1C",
                          "title": "Нужна ли интеграция с 1С",
                          "type": "radios",
                          "variables": [
                            {
                              "varname": "yes",
                              "vartitle": " Да",
                              "next": {
                                "name": "companyName",
                                "title": "Название Вашей компании",
                                "type": "text",
                                "variables": [
                                  {
                                    "varname": "companyName",
                                    "vartitle": "Название компании",
                                    "next": {
                                      "name": "fieldOfActivity",
                                      "title": "Сфера деятельности",
                                      "type": "text",
                                      "variables": [
                                        {
                                          "varname": "fieldOfActivity",
                                          "vartitle": "Сфера деятельности",
                                          "next": {
                                            "name": "yourСompetitors",
                                            "title": "Кто Ваши конкуренты",
                                            "type": "textarea",
                                            "variables": [
                                              {
                                                "varname": "yourСompetitors",
                                                "vartitle": "Кто Ваши конкуренты",
                                                "next": {
                                                  "name": "contacts",
                                                  "title": "Оставьте Ваши контакты",
                                                  "type": "text",
                                                  "variables": [
                                                    {
                                                      "varname": "name",
                                                      "vartitle": "Имя",
                                                      "next": null
                                                    },
                                                    {
                                                      "varname": "phone",
                                                      "datavalidator": "\\d{11}",
                                                      "vartitle": "Телефон",
                                                      "next": null
                                                    },
                                                    {
                                                      "varname": "email",
                                                      "datavalidator": ".+@.+\..+",
                                                      "vartitle": "Электронная почта",
                                                      "next": null
                                                    }
                                                  ]
                                                }
                                              }
                                            ]
                                          }
                                        }
                                      ]
                                    }
                                  }
                                ]
                              }
                            },
                            {
                              "varname": "no",
                              "vartitle": " Нет",
                              "next": {
                                "name": "companyName",
                                "title": "Название Вашей компании",
                                "type": "text",
                                "variables": [
                                  {
                                    "varname": "companyName",
                                    "vartitle": "Название компании",
                                    "next": {
                                      "name": "fieldOfActivity",
                                      "title": "Сфера деятельности",
                                      "type": "text",
                                      "variables": [
                                        {
                                          "varname": "fieldOfActivity",
                                          "vartitle": "Сфера деятельности",
                                          "next": {
                                            "name": "yourСompetitors",
                                            "title": "Кто Ваши конкуренты",
                                            "type": "textarea",
                                            "variables": [
                                              {
                                                "varname": "yourСompetitors",
                                                "vartitle": "Кто Ваши конкуренты",
                                                "next": {
                                                  "name": "contacts",
                                                  "title": "Оставьте Ваши контакты",
                                                  "type": "text",
                                                  "variables": [
                                                    {
                                                      "varname": "name",
                                                      "vartitle": "Имя",
                                                      "next": null
                                                    },
                                                    {
                                                      "varname": "phone",
                                                      "datavalidator": "\\d{11}",
                                                      "vartitle": "Телефон",
                                                      "next": null
                                                    },
                                                    {
                                                      "varname": "email",
                                                      "datavalidator": ".+@.+\..+",
                                                      "vartitle": "Электронная почта",
                                                      "next": null
                                                    }
                                                  ]
                                                }
                                              }
                                            ]
                                          }
                                        }
                                      ]
                                    }
                                  }
                                ]
                              }
                            }
                          ]
                        }
                      },
                      {
                        "varname": "no",
                        "vartitle": "Нет",
                        "next": {
                          "name": "need1C",
                          "title": "Нужна ли интеграция с 1С",
                          "type": "radios",
                          "variables": [
                            {
                              "varname": "yes",
                              "vartitle": " Да",
                              "next": {
                                "name": "companyName",
                                "title": "Название Вашей компании",
                                "type": "text",
                                "variables": [
                                  {
                                    "varname": "companyName",
                                    "vartitle": "Название компании",
                                    "next": {
                                      "name": "fieldOfActivity",
                                      "title": "Сфера деятельности",
                                      "type": "text",
                                      "variables": [
                                        {
                                          "varname": "fieldOfActivity",
                                          "vartitle": "Сфера деятельности",
                                          "next": {
                                            "name": "yourСompetitors",
                                            "title": "Кто Ваши конкуренты",
                                            "type": "textarea",
                                            "variables": [
                                              {
                                                "varname": "yourСompetitors",
                                                "vartitle": "Кто Ваши конкуренты",
                                                "next": {
                                                  "name": "contacts",
                                                  "title": "Оставьте Ваши контакты",
                                                  "type": "text",
                                                  "variables": [
                                                    {
                                                      "varname": "name",
                                                      "vartitle": "Имя",
                                                      "next": null
                                                    },
                                                    {
                                                      "varname": "phone",
                                                      "datavalidator": "\\d{11}",
                                                      "vartitle": "Телефон",
                                                      "next": null
                                                    },
                                                    {
                                                      "varname": "email",
                                                      "datavalidator": ".+@.+\..+",
                                                      "vartitle": "Электронная почта",
                                                      "next": null
                                                    }
                                                  ]
                                                }
                                              }
                                            ]
                                          }
                                        }
                                      ]
                                    }
                                  }
                                ]
                              }
                            },
                            {
                              "varname": "no",
                              "vartitle": " Нет",
                              "next": {
                                "name": "companyName",
                                "title": "Название Вашей компании",
                                "type": "text",
                                "variables": [
                                  {
                                    "varname": "companyName",
                                    "vartitle": "Название компании",
                                    "next": {
                                      "name": "fieldOfActivity",
                                      "title": "Сфера деятельности",
                                      "type": "text",
                                      "variables": [
                                        {
                                          "varname": "fieldOfActivity",
                                          "vartitle": "Сфера деятельности",
                                          "next": {
                                            "name": "yourСompetitors",
                                            "title": "Кто Ваши конкуренты",
                                            "type": "textarea",
                                            "variables": [
                                              {
                                                "varname": "yourСompetitors",
                                                "vartitle": "Кто Ваши конкуренты",
                                                "next": {
                                                  "name": "contacts",
                                                  "title": "Оставьте Ваши контакты",
                                                  "type": "text",
                                                  "variables": [
                                                    {
                                                      "varname": "name",
                                                      "vartitle": "Имя",
                                                      "next": null
                                                    },
                                                    {
                                                      "varname": "phone",
                                                      "datavalidator": "\\d{11}",
                                                      "vartitle": "Телефон",
                                                      "next": null
                                                    },
                                                    {
                                                      "varname": "email",
                                                      "datavalidator": ".+@.+\..+",
                                                      "vartitle": "Электронная почта",
                                                      "next": null
                                                    }
                                                  ]
                                                }
                                              }
                                            ]
                                          }
                                        }
                                      ]
                                    }
                                  }
                                ]
                              }
                            }
                          ]
                        }
                      }
                    ]
                  }
                }
              ]
            }
          }
        ]
      }
    },
    {
      "varname": "internet-advertising",
      "vartitle": "Настроить рекламу в интернете",
      "next": {
        "name": "companyName",
        "title": "Название Вашей компании",
        "type": "text",
        "variables": [
          {
            "varname": "companyName",
            "vartitle": "Название компании",
            "next": {
              "name": "fieldOfActivity",
              "title": "Сфера деятельности",
              "type": "text",
              "variables": [
                {
                  "varname": "fieldOfActivity",
                  "vartitle": "Сфера деятельности",
                  "next": {
                    "name": "yourCity",
                    "title": "В каком городе работает компания",
                    "type": "text",
                    "variables": [
                      {
                        "varname": "yourCity",
                        "vartitle": " Город",
                        "next": {
                          "name": "haveSite",
                          "title": "Есть ли у Вас сайт?",
                          "type": "radios",
                          "variables": [
                            {
                              "varname": "yes",
                              "vartitle": "Да",
                              "next": {
                                "name": "siteAddress",
                                "title": "Введите адрес вашего сайта",
                                "type": "text",
                                "variables": [
                                  {
                                    "varname": "address",
                                    "vartitle": "адрес",
                                    "next": {
                                      "name": "haveSocial",
                                      "title": "Есть ли соц. сети у Вашей компании?",
                                      "type": "radios",
                                      "variables": [
                                        {
                                          "varname": "yes",
                                          "vartitle": "Да",
                                          "next": {
                                            "name": "socialAddress",
                                            "title": "Ссылки на ваши соц. сети",
                                            "type": "text",
                                            "variables": [
                                              {
                                                "varname": "vkAddress",
                                                "datavalidator": ".*",
                                                "vartitle": "Вконтакте",
                                                "next": {
                                                  "name": "yourСompetitors",
                                                  "title": "Кто Ваши конкуренты",
                                                  "type": "textarea",
                                                  "variables": [
                                                    {
                                                      "varname": "yourСompetitors",
                                                      "vartitle": "Кто Ваши конкуренты",
                                                      "next": {
                                                        "name": "contacts",
                                                        "title": "Оставьте Ваши контакты",
                                                        "type": "text",
                                                        "variables": [
                                                          {
                                                            "varname": "name",
                                                            "vartitle": "Имя",
                                                            "next": null
                                                          },
                                                          {
                                                            "varname": "phone",
                                                            "datavalidator": "\\d{11}",
                                                            "vartitle": "Телефон",
                                                            "next": null
                                                          },
                                                          {
                                                            "varname": "email",
                                                            "datavalidator": ".+@.+\..+",
                                                            "vartitle": "Электронная почта",
                                                            "next": null
                                                          }
                                                        ]
                                                      }
                                                    }
                                                  ]
                                                }
                                              },
                                              {
                                                "varname": "instaAsdress",
                                                "datavalidator": ".*",
                                                "vartitle": "Instagram",
                                                "next": {}
                                              },
                                              {
                                                "varname": "fbAddress",
                                                "datavalidator": ".*",
                                                "vartitle": "Facebook",
                                                "next": {}
                                              }
                                            ]
                                          }
                                        },
                                        {
                                          "varname": "no",
                                          "vartitle": "Нет",
                                          "next": {
                                            "name": "yourСompetitors",
                                            "title": "Кто Ваши конкуренты",
                                            "type": "textarea",
                                            "variables": [
                                              {
                                                "varname": "yourСompetitors",
                                                "vartitle": "Кто Ваши конкуренты",
                                                "next": {
                                                  "name": "contacts",
                                                  "title": "Оставьте Ваши контакты",
                                                  "type": "text",
                                                  "variables": [
                                                    {
                                                      "varname": "name",
                                                      "vartitle": "Имя",
                                                      "next": null
                                                    },
                                                    {
                                                      "varname": "phone",
                                                      "datavalidator": "\\d{11}",
                                                      "vartitle": "Телефон",
                                                      "next": null
                                                    },
                                                    {
                                                      "varname": "email",
                                                      "datavalidator": ".+@.+\..+",
                                                      "vartitle": "Электронная почта",
                                                      "next": null
                                                    }
                                                  ]
                                                }
                                              }
                                            ]
                                          }

                                        }
                                      ]
                                    }
                                  }
                                ]
                              }
                            },
                            {
                              "varname": "no",
                              "vartitle": "Нет",
                              "next": {
                                "name": "haveSocial",
                                "title": "Есть ли соц. сети у Вашей компании?",
                                "type": "radios",
                                "variables": [
                                  {
                                    "varname": "yes",
                                    "vartitle": "Да",
                                    "next": {
                                      "name": "socialAddress",
                                      "title": "Ссылки на ваши соц. сети",
                                      "type": "text",
                                      "variables": [
                                        {
                                          "varname": "vkAddress",
                                          "datavalidator": ".*",
                                          "vartitle": "Вконтакте",
                                          "next": {
                                            "name": "yourСompetitors",
                                            "title": "Кто Ваши конкуренты",
                                            "type": "textarea",
                                            "variables": [
                                              {
                                                "varname": "yourСompetitors",
                                                "vartitle": "Кто Ваши конкуренты",
                                                "next": {
                                                  "name": "contacts",
                                                  "title": "Оставьте Ваши контакты",
                                                  "type": "text",
                                                  "variables": [
                                                    {
                                                      "varname": "name",
                                                      "vartitle": "Имя",
                                                      "next": null
                                                    },
                                                    {
                                                      "varname": "phone",
                                                      "datavalidator": "\\d{11}",
                                                      "vartitle": "Телефон",
                                                      "next": null
                                                    },
                                                    {
                                                      "varname": "email",
                                                      "datavalidator": ".+@.+\..+",
                                                      "vartitle": "Электронная почта",
                                                      "next": null
                                                    }
                                                  ]
                                                }
                                              }
                                            ]
                                          }
                                        },
                                        {
                                          "varname": "instaAsdress",
                                          "datavalidator": ".*",
                                          "vartitle": "Instagram",
                                          "next": {}
                                        },
                                        {
                                          "varname": "fbAddress",
                                          "datavalidator": ".*",
                                          "vartitle": "Facebook",
                                          "next": {}
                                        }
                                      ]
                                    }
                                  },
                                  {
                                    "varname": "no",
                                    "vartitle": "Нет",
                                    "next": {
                                      "name": "yourСompetitors",
                                      "title": "Кто Ваши конкуренты",
                                      "type": "textarea",
                                      "variables": [
                                        {
                                          "varname": "yourСompetitors",
                                          "vartitle": "Кто Ваши конкуренты",
                                          "next": {
                                            "name": "contacts",
                                            "title": "Оставьте Ваши контакты",
                                            "type": "text",
                                            "variables": [
                                              {
                                                "varname": "name",
                                                "vartitle": "Имя",
                                                "next": null
                                              },
                                              {
                                                "varname": "phone",
                                                "datavalidator": "\\d{11}",
                                                "vartitle": "Телефон",
                                                "next": null
                                              },
                                              {
                                                "varname": "email",
                                                "datavalidator": ".+@.+\..+",
                                                "vartitle": "Электронная почта",
                                                "next": null
                                              }
                                            ]
                                          }
                                        }
                                      ]
                                    }
                                  }
                                ]
                              }
                            }
                          ]
                        }
                      }
                    ]
                  }
                }
              ]
            }
          }
        ]
      }
    },
    {
      "varname": "lead-social",
      "vartitle": "Вести социальные сети",
      "next": {
        "name": "companyName",
        "title": "Название Вашей компании",
        "type": "text",
        "variables": [
          {
            "varname": "companyName",
            "vartitle": "Название компании",
            "next": {
              "name": "fieldOfActivity",
              "title": "Сфера деятельности",
              "type": "text",
              "variables": [
                {
                  "varname": "fieldOfActivity",
                  "vartitle": "Сфера деятельности",
                  "next": {
                    "name": "yourCity",
                    "title": "В каком городе работает компания",
                    "type": "text",
                    "variables": [
                      {
                        "varname": "yourCity",
                        "vartitle": " Город",
                        "next": {
                          "name": "whichSocial",
                          "title": "Какие соц. сети вы бы хотели вести",
                          "type": "text",
                          "variables": [
                            {
                              "varname": "whichSocial",
                              "vartitle": "Какие соц. сети вы бы хотели вести",
                              "next": {
                                "name": "yourСompetitors",
                                "title": "Кто Ваши конкуренты",
                                "type": "textarea",
                                "variables": [
                                  {
                                    "varname": "yourСompetitors",
                                    "vartitle": "Кто Ваши конкуренты",
                                    "next": {
                                      "name": "contacts",
                                      "title": "Оставьте Ваши контакты",
                                      "type": "text",
                                      "variables": [
                                        {
                                          "varname": "name",
                                          "vartitle": "Имя",
                                          "next": null
                                        },
                                        {
                                          "varname": "phone",
                                          "datavalidator": "\\d{11}",
                                          "vartitle": "Телефон",
                                          "next": null
                                        },
                                        {
                                          "varname": "email",
                                          "datavalidator": ".+@.+\..+",
                                          "vartitle": "Электронная почта",
                                          "next": null
                                        }
                                      ]
                                    }
                                  }
                                ]
                              }
                            }
                          ]
                        }
                      }
                    ]
                  }
                }
              ]
            }
          }
        ]
      }
    },
    {
      "varname": "branding",
      "vartitle": "Брендинг",
      "next": {
        "name": "companyName",
        "title": "Название Вашей компании",
        "type": "text",
        "variables": [
          {
            "varname": "companyName",
            "vartitle": "Название компании",
            "next": {
              "name": "fieldOfActivity",
              "title": "Сфера деятельности",
              "type": "text",
              "variables": [
                {
                  "varname": "fieldOfActivity",
                  "vartitle": "Сфера деятельности",
                  "next": {
                    "name": "yourCity",
                    "title": "В каком городе работает компания",
                    "type": "text",
                    "variables": [
                      {
                        "varname": "yourCity",
                        "vartitle": " Город",
                        "next": {
                          "name": "newOrRenew",
                          "title": "Нужно сделать редизайн существующего бренда или создать новый?",
                          "type": "radios",
                          "variables": [
                            {
                              "varname": "Renew",
                              "vartitle": "Редизайн существующего",
                              "next": {
                                "name": "haveSite",
                                "title": "Есть ли у Вас сайт?",
                                "type": "radios",
                                "variables": [
                                  {
                                    "varname": "yes",
                                    "vartitle": "Да",
                                    "next": {
                                      "name": "siteAddress",
                                      "title": "Введите адрес вашего сайта",
                                      "type": "text",
                                      "variables": [
                                        {
                                          "varname": "address",
                                          "vartitle": "адрес",
                                          "next": {
                                            "name": "yourСompetitors",
                                            "title": "Кто Ваши конкуренты",
                                            "type": "textarea",
                                            "variables": [
                                              {
                                                "varname": "yourСompetitors",
                                                "vartitle": "Кто Ваши конкуренты",
                                                "next": {
                                                  "name": "benefits",
                                                  "title": "Чем отличается Ваш бренд от других?",
                                                  "type": "textarea",
                                                  "variables": [
                                                    {
                                                      "varname": "benefits",
                                                      "vartitle": "Чем отличается Ваш бренд от других?",
                                                      "next": {
                                                        "name": "contacts",
                                                        "title": "Оставьте Ваши контакты",
                                                        "type": "text",
                                                        "variables": [
                                                          {
                                                            "varname": "name",
                                                            "vartitle": "Имя",
                                                            "next": null
                                                          },
                                                          {
                                                            "varname": "phone",
                                                            "datavalidator": "\\d{11}",
                                                            "vartitle": "Телефон",
                                                            "next": null
                                                          },
                                                          {
                                                            "varname": "email",
                                                            "datavalidator": ".+@.+\..+",
                                                            "vartitle": "Электронная почта",
                                                            "next": null
                                                          }
                                                        ]
                                                      }
                                                    }
                                                  ]
                                                }
                                              }
                                            ]
                                          }
                                        }
                                      ]
                                    }
                                  },
                                  {
                                    "varname": "no",
                                    "vartitle": "Нет",
                                    "next": {
                                      "name": "yourСompetitors",
                                      "title": "Кто Ваши конкуренты",
                                      "type": "textarea",
                                      "variables": [
                                        {
                                          "varname": "yourСompetitors",
                                          "vartitle": "Кто Ваши конкуренты",
                                          "next": {
                                            "name": "benefits",
                                            "title": "Чем отличается Ваш бренд от других?",
                                            "type": "textarea",
                                            "variables": [
                                              {
                                                "varname": "benefits",
                                                "vartitle": "Чем отличается Ваш бренд от других?",
                                                "next": {
                                                  "name": "contacts",
                                                  "title": "Оставьте Ваши контакты",
                                                  "type": "text",
                                                  "variables": [
                                                    {
                                                      "varname": "name",
                                                      "vartitle": "Имя",
                                                      "next": null
                                                    },
                                                    {
                                                      "varname": "phone",
                                                      "datavalidator": "\\d{11}",
                                                      "vartitle": "Телефон",
                                                      "next": null
                                                    },
                                                    {
                                                      "varname": "email",
                                                      "datavalidator": ".+@.+\..+",
                                                      "vartitle": "Электронная почта",
                                                      "next": null
                                                    }
                                                  ]
                                                }
                                              }
                                            ]
                                          }
                                        }
                                      ]
                                    }
                                  }
                                ]
                              }
                            },
                            {
                              "varname": "new",
                              "vartitle": "Создать новый",
                              "next": {
                                "name": "haveSite",
                                "title": "Есть ли у Вас сайт?",
                                "type": "radios",
                                "variables": [
                                  {
                                    "varname": "yes",
                                    "vartitle": "Да",
                                    "next": {
                                      "name": "siteAddress",
                                      "title": "Введите адрес вашего сайта",
                                      "type": "text",
                                      "variables": [
                                        {
                                          "varname": "address",
                                          "vartitle": "адрес",
                                          "next": {
                                            "name": "yourСompetitors",
                                            "title": "Кто Ваши конкуренты",
                                            "type": "textarea",
                                            "variables": [
                                              {
                                                "varname": "yourСompetitors",
                                                "vartitle": "Кто Ваши конкуренты",
                                                "next": {
                                                  "name": "benefits",
                                                  "title": "Чем отличается Ваш бренд от других?",
                                                  "type": "textarea",
                                                  "variables": [
                                                    {
                                                      "varname": "benefits",
                                                      "vartitle": "Чем отличается Ваш бренд от других?",
                                                      "next": {
                                                        "name": "contacts",
                                                        "title": "Оставьте Ваши контакты",
                                                        "type": "text",
                                                        "variables": [
                                                          {
                                                            "varname": "name",
                                                            "vartitle": "Имя",
                                                            "next": null
                                                          },
                                                          {
                                                            "varname": "phone",
                                                            "datavalidator": "\\d{11}",
                                                            "vartitle": "Телефон",
                                                            "next": null
                                                          },
                                                          {
                                                            "varname": "email",
                                                            "datavalidator": ".+@.+\..+",
                                                            "vartitle": "Электронная почта",
                                                            "next": null
                                                          }
                                                        ]
                                                      }
                                                    }
                                                  ]
                                                }
                                              }
                                            ]
                                          }
                                        }
                                      ]
                                    }
                                  },
                                  {
                                    "varname": "no",
                                    "vartitle": "Нет",
                                    "next": {
                                      "name": "yourСompetitors",
                                      "title": "Кто Ваши конкуренты",
                                      "type": "textarea",
                                      "variables": [
                                        {
                                          "varname": "yourСompetitors",
                                          "vartitle": "Кто Ваши конкуренты",
                                          "next": {
                                            "name": "benefits",
                                            "title": "Чем отличается Ваш бренд от других?",
                                            "type": "textarea",
                                            "variables": [
                                              {
                                                "varname": "benefits",
                                                "vartitle": "Чем отличается Ваш бренд от других?",
                                                "next": {
                                                  "name": "contacts",
                                                  "title": "Оставьте Ваши контакты",
                                                  "type": "text",
                                                  "variables": [
                                                    {
                                                      "varname": "name",
                                                      "vartitle": "Имя",
                                                      "next": null
                                                    },
                                                    {
                                                      "varname": "phone",
                                                      "datavalidator": "\\d{11}",
                                                      "vartitle": "Телефон",
                                                      "next": null
                                                    },
                                                    {
                                                      "varname": "email",
                                                      "datavalidator": ".+@.+\..+",
                                                      "vartitle": "Электронная почта",
                                                      "next": null
                                                    }
                                                  ]
                                                }
                                              }
                                            ]
                                          }
                                        }
                                      ]
                                    }
                                  }
                                ]
                              }
                            }
                          ]
                        }
                      }
                    ]
                  }
                }
              ]
            }
          }
        ]
      }
    }
  ]
}